Aditzak/__init__.py
Aditzak/analyzer.py
Aditzak/builder.py
Aditzak/nk3.json
Aditzak/nor.json
Aditzak-0.3.32.dist-info/LICENSE
Aditzak-0.3.32.dist-info/METADATA
Aditzak-0.3.32.dist-info/WHEEL
Aditzak-0.3.32.dist-info/top_level.txt
Aditzak-0.3.32.dist-info/RECORD
