Metadata-Version: 2.1
Name: Aditzak
Version: 0.3.32
Summary: A Python package to analyse and build Euskera/Basque verbs.
Home-page: https://github.com/HCook86/Aditzak/
Author: 
Author-email: aditzaksoftware@gmail.com
License: BSD 2-clause
Classifier: Development Status :: 1 - Planning
Classifier: Intended Audience :: Developers
Classifier: License :: OSI Approved :: BSD License
Classifier: Operating System :: OS Independent
Classifier: Programming Language :: Python :: 3
License-File: LICENSE
